easydl/__init__.py
easydl/proto/__init__.py
easydl/proto/protobuf_3_20_3/__init__.py
easydl/proto/protobuf_3_20_3/easydl_pb2.py
easydl/proto/protobuf_3_20_3/easydl_pb2_grpc.py
easydl/proto/protobuf_4_25_3/__init__.py
easydl/proto/protobuf_4_25_3/easydl_pb2.py
easydl/proto/protobuf_4_25_3/easydl_pb2_grpc.py
easydl/python/__init__.py
easydl/python/common/__init__.py
easydl/python/common/constants.py
easydl/python/common/grpc_utils.py
easydl/python/common/log_utils.py
easydl/python/external_optimizer/__init__.py
easydl/python/external_optimizer/main.py
easydl/python/external_optimizer/optimizer.py
easydl/python/external_optimizer/rl_env_manager.py
easydl/python/external_optimizer/servicer.py
easydl/python/runtime/__init__.py
easydl/python/runtime/easydl_client.py
easydl/python/runtime/metric_collector.py
easydl/python/runtime/resource_optimizer.py
elasticai_api/__init__.py
elasticai_api/common/__init__.py
elasticai_api/common/base_controller.py
elasticai_api/common/constants.py
elasticai_api/common/data_shard_service.py
elasticai_api/common/master_client.py
elasticai_api/common/pod_relauncher.py
elasticai_api/common/remote_lock.py
elasticai_api/common/synchronization.py
elasticai_api/common/training_monitor.py
elasticai_api/io/__init__.py
elasticai_api/io/recordio_reader.py
elasticai_api/proto/__init__.py
elasticai_api/proto/protobuf_3_20_3/__init__.py
elasticai_api/proto/protobuf_3_20_3/elasticai_api_pb2.py
elasticai_api/proto/protobuf_3_20_3/elasticai_api_pb2_grpc.py
elasticai_api/proto/protobuf_4_25_3/__init__.py
elasticai_api/proto/protobuf_4_25_3/elasticai_api_pb2.py
elasticai_api/proto/protobuf_4_25_3/elasticai_api_pb2_grpc.py
elasticai_api/pytorch/DDP_controller.py
elasticai_api/pytorch/__init__.py
elasticai_api/pytorch/controller.py
elasticai_api/pytorch/dataset.py
elasticai_api/pytorch/elastic_worker.py
elasticai_api/pytorch/optimizer.py
elasticai_api/pytorch/prestop.py
elasticai_api/scripts/__init__.py
elasticai_api/scripts/check_hardware.py
elasticai_api-1.4.2.dist-info/LICENSE
elasticai_api-1.4.2.dist-info/METADATA
elasticai_api-1.4.2.dist-info/WHEEL
elasticai_api-1.4.2.dist-info/top_level.txt
elasticai_api-1.4.2.dist-info/RECORD
